dim_relayout.py
dim_relayout-4.0.0.dist-info/METADATA
dim_relayout-4.0.0.dist-info/WHEEL
dim_relayout-4.0.0.dist-info/licenses/LICENSE
dim_relayout-4.0.0.dist-info/RECORD
