Metadata-Version: 2.3
Name: dim_relayout
Version: 4.0.0
Summary: dim_gui
Author-email: YingkeHuang <ykhuang@ihep.ac.cn>
License-File: LICENSE
Classifier: License :: OSI Approved :: MIT License
Classifier: Programming Language :: Python :: 3
Requires-Python: >=3.6
